MANIFEST.in
README.txt
setup.cfg
setup.py
ROIWidgets/__init__.py
ROIWidgets/__init__.pyc
ROIWidgets.egg-info/PKG-INFO
ROIWidgets.egg-info/SOURCES.txt
ROIWidgets.egg-info/dependency_links.txt
ROIWidgets.egg-info/requires.txt
ROIWidgets.egg-info/top_level.txt
static/components/raphael/raphael.js
static/widgets/js/roi_init.js
static/widgets/js/widget_roi.js
static/widgets/js/widget_roi_ellipse.js
static/widgets/js/widget_roi_line.js
static/widgets/js/widget_roi_polygon.js
static/widgets/js/widget_roi_rect.js