Metadata-Version: 1.1
Name: ROIWidgets
Version: 0.1.9
Summary: IPython notebook Region of Interest widgets
Home-page: https://pypi.python.org/pypi/ROIWidgets
Author: Leon Avery
Author-email: lavery3@vcu.edu
License: UNKNOWN
Platform: UNKNOWN
Classifier: Development Status :: 2 - Pre-Alpha
Classifier: Environment :: Web Environment
Classifier: Framework :: IPython
Classifier: Intended Audience :: Developers
Classifier: Intended Audience :: Science/Research
Classifier: License :: Free for non-commercial use
Classifier: Programming Language :: Python
Classifier: Programming Language :: JavaScript
Classifier: Topic :: Software Development :: Widget Sets
Requires: ipython
Requires: Pillow
Requires: hashlib
Requires: numpy
Requires: IPython
Requires: IPython.html
Requires: IPython.utils.traitlets
